deflect/__init__.py
deflect/client.py
deflect-0.1.0.dist-info/METADATA
deflect-0.1.0.dist-info/WHEEL
deflect-0.1.0.dist-info/top_level.txt
deflect-0.1.0.dist-info/RECORD
