Metadata-Version: 2.4
Name: deflect
Version: 0.1.0
Summary: Official Deflect Bot Protection SDK for Python
Author: Deflect
License: MIT
Project-URL: Homepage, https://docs.deflect.bot/
Project-URL: Source, https://github.com/deflectbot/deflect-python
Project-URL: Issues, https://github.com/deflectbot/deflect-python/issues
Keywords: deflect,bot,security,antibot
Classifier: Programming Language :: Python :: 3
Classifier: Programming Language :: Python :: 3 :: Only
Classifier: Programming Language :: Python :: 3.8
Classifier: Programming Language :: Python :: 3.9
Classifier: Programming Language :: Python :: 3.10
Classifier: Programming Language :: Python :: 3.11
Classifier: Programming Language :: Python :: 3.12
Classifier: License :: OSI Approved :: MIT License
Classifier: Intended Audience :: Developers
Classifier: Topic :: Security
Requires-Python: >=3.8
Requires-Dist: httpx<0.28.0,>=0.27.0
Provides-Extra: async
Requires-Dist: httpx[http2]<0.28.0,>=0.27.0; extra == "async"
Provides-Extra: test
Requires-Dist: pytest>=6.0; extra == "test"
Requires-Dist: pytest-asyncio>=0.21.0; extra == "test"
